{"type":"Scene","props":{"x":0,"width":1242,"runtime":"game/pages/Shop/ShopUI.ts","height":2208},"compId":2,"child":[{"type":"Script","props":{"y":0,"x":0,"runtime":"game/common/SetSceneWH.ts"},"compId":89},{"type":"Script","props":{"y":0,"x":0,"runtime":"game/pages/Shop/Shop.ts"},"compId":94},{"type":"Image","props":{"y":0,"x":0,"top":0,"skin":"images/common/bg.jpg","right":0,"name":"bg","left":0,"bottom":0},"compId":4},{"type":"Image","props":{"y":0,"top":0,"skin":"images/common/top.png","right":0.1,"name":"hd","left":0.1,"height":195},"compId":85,"child":[{"type":"Image","props":{"width":1242,"top":5,"right":0,"name":"titleBox","left":0,"height":153,"bottom":0},"compId":86,"child":[{"type":"Image","props":{"skin":"images/common/title_shop.png","name":"title","centerY":0,"centerX":0},"compId":87},{"type":"Image","props":{"x":656,"var":"shop_back_btn","skin":"images/common/back.png","name":"back_btn","left":85,"centerY":-10},"compId":27,"child":[{"type":"Script","props":{"runtime":"game/common/Back.ts"},"compId":90}]}]},{"type":"Script","props":{"runtime":"game/common/setHd.ts"},"compId":91}]},{"type":"Image","props":{"width":1126,"var":"shop_content","top":420,"skin":"images/common/bg2.png","right":58,"name":"list_bg","left":58,"height":1000,"sizeGrid":"60,60,60,60"},"compId":77,"child":[{"type":"Image","props":{"top":45,"skin":"images/me/bg.png","right":45,"name":"bg2","left":45,"bottom":45,"sizeGrid":"43,20,32,20"},"compId":92,"child":[{"type":"List","props":{"var":"s_list","top":30,"right":60,"name":"list","left":60,"elasticEnabled":true,"bottom":20},"compId":84,"child":[{"type":"Box","props":{"right":0,"renderType":"render","name":"listBox","left":0,"height":140},"compId":78,"child":[{"type":"Image","props":{"skin":"images/common/coinIcon.png","name":"icon","centerY":0},"compId":79},{"type":"Image","props":{"skin":"images/common/fenge.png","name":"line","centerX":0,"bottom":0},"compId":80},{"type":"Image","props":{"name":"text","centerY":0,"centerX":0},"compId":81},{"type":"Image","props":{"width":200,"right":0,"name":"btn","height":100,"centerY":0},"compId":82,"child":[{"type":"Image","props":{"name":"value","centerY":0,"centerX":0},"compId":83}]}]}]}]}]}],"loadList":["images/common/bg.jpg","images/common/top.png","images/common/title_shop.png","images/common/back.png","images/common/bg2.png","images/me/bg.png","images/common/coinIcon.png","images/common/fenge.png"],"loadList3D":[]}